setup.py
pvim/__init__.py
pvim/__main__.py
pvim/completion.py
pvim/editor.py
pvim/editor_buffer.py
pvim/enums.py
pvim/help.py
pvim/key_bindings.py
pvim/layout.py
pvim/lexer.py
pvim/rc_file.py
pvim/reporting.py
pvim/style.py
pvim/welcome_message.py
pvim/window_arrangement.py
pvim.egg-info/PKG-INFO
pvim.egg-info/SOURCES.txt
pvim.egg-info/dependency_links.txt
pvim.egg-info/entry_points.txt
pvim.egg-info/requires.txt
pvim.egg-info/top_level.txt
pvim/commands/__init__.py
pvim/commands/commands.py
pvim/commands/completer.py
pvim/commands/grammar.py
pvim/commands/handler.py
pvim/commands/lexer.py
pvim/commands/preview.py
pvim/entry_points/__init__.py
pvim/entry_points/run_pyvim.py
pvim/io/__init__.py
pvim/io/backends.py
pvim/io/base.py