Metadata-Version: 2.1
Name: pvim
Version: 3.9
Summary: Pure Python Vim Implementation
Author: Intel
